odoo/addons/stock_warehouse_calendar/README.rst
odoo/addons/stock_warehouse_calendar/__init__.py
odoo/addons/stock_warehouse_calendar/__manifest__.py
odoo/addons/stock_warehouse_calendar/i18n/it.po
odoo/addons/stock_warehouse_calendar/i18n/stock_warehouse_calendar.pot
odoo/addons/stock_warehouse_calendar/i18n/zh_CN.po
odoo/addons/stock_warehouse_calendar/models/__init__.py
odoo/addons/stock_warehouse_calendar/models/stock_rule.py
odoo/addons/stock_warehouse_calendar/models/stock_warehouse.py
odoo/addons/stock_warehouse_calendar/readme/CONFIGURE.rst
odoo/addons/stock_warehouse_calendar/readme/CONTRIBUTORS.rst
odoo/addons/stock_warehouse_calendar/readme/DESCRIPTION.rst
odoo/addons/stock_warehouse_calendar/readme/USAGE.rst
odoo/addons/stock_warehouse_calendar/static/description/icon.png
odoo/addons/stock_warehouse_calendar/static/description/index.html
odoo/addons/stock_warehouse_calendar/tests/__init__.py
odoo/addons/stock_warehouse_calendar/tests/test_stock_warehouse_calendar.py
odoo/addons/stock_warehouse_calendar/views/stock_warehouse_views.xml
odoo14_addon_stock_warehouse_calendar-14.0.1.0.2.dev12.dist-info/METADATA
odoo14_addon_stock_warehouse_calendar-14.0.1.0.2.dev12.dist-info/WHEEL
odoo14_addon_stock_warehouse_calendar-14.0.1.0.2.dev12.dist-info/top_level.txt
odoo14_addon_stock_warehouse_calendar-14.0.1.0.2.dev12.dist-info/RECORD
